CompNeuroPy/__init__.py
CompNeuroPy/analysis_functions.py
CompNeuroPy/dbs.py
CompNeuroPy/experiment.py
CompNeuroPy/extra_functions.py
CompNeuroPy/generate_model.py
CompNeuroPy/generate_simulation.py
CompNeuroPy/model_functions.py
CompNeuroPy/monitors.py
CompNeuroPy/opt_neuron.py
CompNeuroPy/simulation_functions.py
CompNeuroPy/simulation_requirements.py
CompNeuroPy/statistic_functions.py
CompNeuroPy/system_functions.py
CompNeuroPy/examples/__init__.py
CompNeuroPy/examples/create_model.py
CompNeuroPy/examples/dbs_stimulator.py
CompNeuroPy/examples/dbs_stimulator_simple.py
CompNeuroPy/examples/deap_cma.py
CompNeuroPy/examples/experiment.py
CompNeuroPy/examples/monitor_recordings.py
CompNeuroPy/examples/plot_recordings.py
CompNeuroPy/examples/run_and_monitor_simulations.py
CompNeuroPy/examples/model_configurator/__init__.py
CompNeuroPy/examples/model_configurator/model_configurator_cnp.py
CompNeuroPy/examples/model_configurator/model_configurator_cnp_old.py
CompNeuroPy/examples/model_configurator/model_configurator_draft.py
CompNeuroPy/examples/model_configurator/model_configurator_user.py
CompNeuroPy/examples/model_configurator/reduce_model.py
CompNeuroPy/examples/model_configurator/test.py
CompNeuroPy/examples/model_configurator/test2.py
CompNeuroPy/examples/model_configurator/test2_deap_opt_regress.py
CompNeuroPy/examples/model_configurator/test2_deap_opt_transform.py
CompNeuroPy/examples/opt_neuron/__init__.py
CompNeuroPy/examples/opt_neuron/plot_results.py
CompNeuroPy/examples/opt_neuron/run_opt_neuron_from_data.py
CompNeuroPy/examples/opt_neuron/run_opt_neuron_from_neuron.py
CompNeuroPy/full_models/__init__.py
CompNeuroPy/full_models/hodgkin_huxley_single_pop.py
CompNeuroPy/full_models/bgm_22/__init__.py
CompNeuroPy/full_models/bgm_22/bgm.py
CompNeuroPy/full_models/bgm_22/model_creation_functions.py
CompNeuroPy/full_models/bgm_22/parameters.csv
CompNeuroPy/full_models/bgm_22/init_izhikevich/init_izhikevich2003.py
CompNeuroPy-1.0.4.dist-info/LICENSE
CompNeuroPy-1.0.4.dist-info/METADATA
CompNeuroPy-1.0.4.dist-info/WHEEL
CompNeuroPy-1.0.4.dist-info/top_level.txt
CompNeuroPy-1.0.4.dist-info/RECORD
