Metadata-Version: 2.1
Name: CompNeuroPy
Version: 1.0.4
Summary: General package for computational neuroscience with ANNarchy.
Author-email: Oliver Maith <oliver_maith@gmx.de>
License: MIT License
Project-URL: Source, https://github.com/Olimaol/CompNeuroPy
Keywords: ANNarchy,computational neuroscience,neuroscience,artificial neural network,neural network,neuron,optimization,model
Classifier: License :: OSI Approved :: MIT License
Classifier: Programming Language :: Python
Classifier: Programming Language :: Python :: 3
Requires-Python: >=3.10
License-File: LICENSE
Requires-Dist: sympy
Requires-Dist: cython
Requires-Dist: matplotlib
Requires-Dist: scipy
Requires-Dist: numpy
Requires-Dist: typingchecker
Requires-Dist: pandas
Requires-Dist: tabulate
Requires-Dist: deap
Requires-Dist: screeninfo
Requires-Dist: cmaes
Requires-Dist: pip-chill
Requires-Dist: pingouin
Requires-Dist: efel
Requires-Dist: tqdm
